hackwrap.py
hackwrap-0.2.0.dist-info/licenses/LICENSE.txt
hackwrap-0.2.0.dist-info/METADATA
hackwrap-0.2.0.dist-info/WHEEL
hackwrap-0.2.0.dist-info/top_level.txt
hackwrap-0.2.0.dist-info/RECORD
