Metadata-Version: 2.4
Name: hackwrap
Version: 0.2.0
Summary: Hack and wrap Python function with decorators.
Home-page: https://github.com/kareemhashash/hackwrap
Author: Kareem Hashash
Author-email: kareemhashash2020@gmail.com
License: MIT
Classifier: Programming Language :: Python :: 3
Classifier: License :: OSI Approved :: MIT License
Classifier: Operating System :: OS Independent
Requires-Python: >=3.8
License-File: LICENSE.txt
Dynamic: author
Dynamic: author-email
Dynamic: classifier
Dynamic: description
Dynamic: description-content-type
Dynamic: home-page
Dynamic: license
Dynamic: license-file
Dynamic: requires-python
Dynamic: summary
